useful_types/__init__.py
useful_types/experimental.py
useful_types/py.typed
useful_types-0.2.0.dist-info/LICENSE
useful_types-0.2.0.dist-info/WHEEL
useful_types-0.2.0.dist-info/METADATA
useful_types-0.2.0.dist-info/RECORD
