Metadata-Version: 2.1
Name: useful_types
Version: 0.2.0
Summary: A collection of useful types.
Author: The Python typing community
Requires-Python: >=3.8
Requires-Dist: typing_extensions >= 4.7
Project-URL: changelog, https://github.com/hauntsaninja/useful_types/blob/main/CHANGELOG.md
Project-URL: homepage, https://github.com/hauntsaninja/useful_types
Project-URL: repository, https://github.com/hauntsaninja/useful_types
